{
  "schemaVersion": 2,
  "backend": {
    "version": "1.1.52",
    "downloadUrl": "https://github.com/orgs/Solfins-dev/packages/container/package/3dx-gateway",
    "changelog": "Durable one-click update: the host updater now reads the live compose set, always reports a real result (no more stuck 'downloading'), and self-recovers from token/overlay drift. After updating, a one-time host step refreshes the helper (see release notes).",
    "sha256": null
  },
  "cadBridge": {
    "version": "1.8.94",
    "downloadUrl": "https://github.com/Solfins-dev/3dx-gateway-updates/releases/download/cadbridge-v1.8.94/CadBridge-Setup.zip",
    "changelog": "Resolve virtual components by their stable child name so STEP and 3D PDF are produced for them (fixes the in-session vs BOM parent-name mismatch that left them missing on a fresh cache).",
    "sha256": "4907019c7a3725ea2383c9fa9ec030f857ef8591bddb9acf4951561187e5ff3a"
  }
}